{"singleUseItemsInfo": {"title": "Add utensils, straws, etc."}, "sectionEntitiesMap": {"44900d29-2bfc-4ece-962c-cd1a7f3f9b4e": {"ff1f572b-05ea-42c0-adac-dd8b7e3163d7": {"description": "", "imageUrl": "", "price": 180, "title": "Santal Juices", "uuid": "ff1f572b-05ea-42c0-adac-dd8b7e3163d7", "nutritionalInfo": {"allergens": "", "displayString": ""}, "suspendReason": null, "suspendUntil": 0, "classifications": []}, "91fe261b-05d2-4c09-a2bc-9d4a7c8376ec": {"description": "", "imageUrl": "", "price": 120, "title": "S. Benedetto Sparkling Water", "uuid": "91fe261b-05d2-4c09-a2bc-9d4a7c8376ec", "nutritionalInfo": {"allergens": "", "displayString": ""}, "suspendReason": null, "suspendUntil": 0, "classifications": []}, "ce390917-c73a-4295-b843-ac9860d36c3a": {"description": "italian Roast beef, rucola salad, Buffalo mozzarella, sun dried tomatoes balsamic and olive oil.", "imageUrl": "", "price": 1250, "title": "Roast Beef Salad", "uuid": "ce390917-c73a-4295-b843-ac9860d36c3a", "nutritionalInfo": {"allergens": "", "displayString": ""}, "suspendReason": null, "suspendUntil": 0, "classifications": []}, "24320977-a738-4492-920f-257200b527f5": {"description": "Bresaola (cured beef), rucola salad, parmesan cheese, e.v. olive oil, and lemon juice.", "imageUrl": "", "price": 850, "title": "Valtellina Panini", "uuid": "24320977-a738-4492-920f-257200b527f5", "nutritionalInfo": {"allergens": "", "displayString": ""}, "suspendReason": null, "suspendUntil": 0, "classifications": []}, "6967df7d-c3a9-4727-930d-a4c4c4638a59": {"description": "Rucola salad, grilled aubergine, peppers, sun-dried tomato, artichokes, and balsamic vinegar.", "imageUrl": "", "price": 1150, "title": "Roasted Vegetable Salad", "uuid": "6967df7d-c3a9-4727-930d-a4c4c4638a59", "nutritionalInfo": {"allergens": "", "displayString": ""}, "suspendReason": null, "suspendUntil": 0, "classifications": []}, "408a244e-30f4-4525-aef1-776e990f455a": {"description": "With roasted ham with herbs and emmenthal cheese. With ham and cheese.", "imageUrl": "", "price": 480, "title": "Croissant", "uuid": "408a244e-30f4-4525-aef1-776e990f455a", "nutritionalInfo": {"allergens": "", "displayString": ""}, "suspendReason": null, "suspendUntil": 0, "classifications": []}, "18f91770-4f91-449a-9448-a00e63b02ff2": {"description": "Roasted peppers, grilled aubergine, grilled courgette, and rucola salad.", "imageUrl": "", "price": 850, "title": "Napoli Panini", "uuid": "18f91770-4f91-449a-9448-a00e63b02ff2", "nutritionalInfo": {"allergens": "", "displayString": ""}, "suspendReason": null, "suspendUntil": 0, "endorsement": {"text": "Vegetarian", "iconUrl": "https://uber-test.s3.amazonaws.com/badge_healthy@3x.png"}, "classifications": []}, "ce5348f3-47ff-47e7-997f-a382c5440d20": {"description": "Fresh mozzarella, pesto sauce, sun dried tomato, and rucola salad.", "imageUrl": "", "price": 850, "title": "Tricolore Panini", "uuid": "ce5348f3-47ff-47e7-997f-a382c5440d20", "nutritionalInfo": {"allergens": "", "displayString": ""}, "suspendReason": null, "suspendUntil": 0, "endorsement": {"text": "Vegetarian", "iconUrl": "https://uber-test.s3.amazonaws.com/badge_healthy@3x.png"}, "classifications": []}, "132e5c00-8a07-449e-9293-7391d39ed789": {"description": "With spaghetti or rice.", "imageUrl": "", "price": 1020, "title": "Spicy Prawns", "uuid": "132e5c00-8a07-449e-9293-7391d39ed789", "nutritionalInfo": {"allergens": "", "displayString": ""}, "suspendReason": null, "suspendUntil": 0, "endorsement": {"text": "Spicy", "iconUrl": "https://uber-test.s3.amazonaws.com/badge_check@3x.png"}, "classifications": []}, "f5b22713-fac9-4d23-80e8-af77aef0f1b0": {"description": "", "imageUrl": "", "price": 350, "title": "Carrots Cake", "uuid": "f5b22713-fac9-4d23-80e8-af77aef0f1b0", "nutritionalInfo": {"allergens": "", "displayString": ""}, "suspendReason": null, "suspendUntil": 0, "classifications": []}, "7e4f9038-cd60-4f16-81d7-b1f52170a6b0": {"description": "", "imageUrl": "", "price": 180, "title": "S.Benedetto Iced Tea", "uuid": "7e4f9038-cd60-4f16-81d7-b1f52170a6b0", "nutritionalInfo": {"allergens": "", "displayString": ""}, "suspendReason": null, "suspendUntil": 0, "classifications": []}, "5bbff582-1c0b-4fa8-8898-05db44ab7e14": {"description": "Choco, lemon, and pistachio.", "imageUrl": "", "price": 120, "title": "Sfogliatelle", "uuid": "5bbff582-1c0b-4fa8-8898-05db44ab7e14", "nutritionalInfo": {"allergens": "", "displayString": ""}, "suspendReason": null, "suspendUntil": 0, "classifications": []}, "da15367d-0ffc-459e-9b0f-49f8146eea02": {"description": "", "imageUrl": "", "price": 300, "title": "Santal Juices (1 L)", "uuid": "da15367d-0ffc-459e-9b0f-49f8146eea02", "nutritionalInfo": {"allergens": "", "displayString": ""}, "suspendReason": null, "suspendUntil": 0, "classifications": []}, "8abe6aef-3387-4cdb-a92d-d9f82e6cf31b": {"description": "Bottles.", "imageUrl": "", "price": 180, "title": "Cocal Cola Zero", "uuid": "8abe6aef-3387-4cdb-a92d-d9f82e6cf31b", "nutritionalInfo": {"allergens": "", "displayString": ""}, "suspendReason": null, "suspendUntil": 0, "classifications": []}, "eff3c868-5bf3-40b0-9012-f17b91384e47": {"description": "", "imageUrl": "", "price": 350, "title": "Apple Pie", "uuid": "eff3c868-5bf3-40b0-9012-f17b91384e47", "nutritionalInfo": {"allergens": "", "displayString": ""}, "suspendReason": null, "suspendUntil": 0, "classifications": []}, "8392f684-396f-4afb-bc55-81cc35df1f33": {"description": "Chicken escalope, pesto sauce, and fresh mozzarella.", "imageUrl": "", "price": 850, "title": "Bari Panini", "uuid": "8392f684-396f-4afb-bc55-81cc35df1f33", "nutritionalInfo": {"allergens": "", "displayString": ""}, "suspendReason": null, "suspendUntil": 0, "classifications": []}, "840f2a99-4eef-41e7-b57b-b11c9d889595": {"description": "", "imageUrl": "", "price": 180, "title": "Chocolate Biscuit", "uuid": "840f2a99-4eef-41e7-b57b-b11c9d889595", "nutritionalInfo": {"allergens": "", "displayString": ""}, "suspendReason": null, "suspendUntil": 0, "classifications": []}, "b7076d8f-2fdb-4ae3-b6a8-5816cac85a06": {"description": "", "imageUrl": "", "price": 1080, "title": "Free Range Scrambled Eggs on Toast", "uuid": "b7076d8f-2fdb-4ae3-b6a8-5816cac85a06", "nutritionalInfo": {"allergens": "", "displayString": ""}, "suspendReason": null, "suspendUntil": 0, "classifications": []}, "ced64950-deda-4996-8193-96e622b94a9f": {"description": "", "imageUrl": "", "price": 960, "title": "Homemade Meatballs", "uuid": "ced64950-deda-4996-8193-96e622b94a9f", "nutritionalInfo": {"allergens": "", "displayString": ""}, "suspendReason": null, "suspendUntil": 0, "classifications": []}, "4ef885f7-eedf-4464-a98b-a05f0896e812": {"description": "Mortadella, artichokes, and rucola.", "imageUrl": "", "price": 850, "title": "Bologna Panini", "uuid": "4ef885f7-eedf-4464-a98b-a05f0896e812", "nutritionalInfo": {"allergens": "", "displayString": ""}, "suspendReason": null, "suspendUntil": 0, "classifications": []}, "5ce22712-de1d-4a7d-ab71-b076d33e2414": {"description": "", "imageUrl": "", "price": 850, "title": "Aubergine Parmigiana", "uuid": "5ce22712-de1d-4a7d-ab71-b076d33e2414", "nutritionalInfo": {"allergens": "", "displayString": ""}, "suspendReason": null, "suspendUntil": 0, "classifications": []}, "eba39688-a77a-4f6a-ba35-f35f9874d077": {"description": "", "imageUrl": "", "price": 1080, "title": "Chicken Milanese and Side", "uuid": "eba39688-a77a-4f6a-ba35-f35f9874d077", "nutritionalInfo": {"allergens": "", "displayString": ""}, "suspendReason": null, "suspendUntil": 0, "classifications": []}, "6d6da4b8-392e-40c0-aa90-ba1a4d402836": {"description": "", "imageUrl": "", "price": 720, "title": "Meat Lasagna", "uuid": "6d6da4b8-392e-40c0-aa90-ba1a4d402836", "nutritionalInfo": {"allergens": "", "displayString": ""}, "suspendReason": null, "suspendUntil": 0, "classifications": []}, "19d87344-b6fa-4f0f-a30e-524f4e21862e": {"description": "Blue cheese grilled aubergine fresh tomato rucola salad.", "imageUrl": "", "price": 850, "title": "Docelatte Panini", "uuid": "19d87344-b6fa-4f0f-a30e-524f4e21862e", "nutritionalInfo": {"allergens": "", "displayString": ""}, "suspendReason": null, "suspendUntil": 0, "endorsement": {"text": "Vegetarian", "iconUrl": "https://uber-test.s3.amazonaws.com/badge_healthy@3x.png"}, "classifications": []}, "f25cf43a-afc3-473d-9314-3a1a99ffe13b": {"description": "Italian tuna, aubergine, fresh tomatoes, artichoke, rucola salad, and roasted peppers dressed with olive oil and balsamic vinegar .", "imageUrl": "", "price": 1150, "title": "Tuna Salad", "uuid": "f25cf43a-afc3-473d-9314-3a1a99ffe13b", "nutritionalInfo": {"allergens": "", "displayString": ""}, "suspendReason": null, "suspendUntil": 0, "classifications": []}, "bc626897-39ac-40cc-b487-2ef219a5fd0c": {"description": "With butter and jam.", "imageUrl": "", "price": 395, "title": "Toasted Italian Ciabatta Bread", "uuid": "bc626897-39ac-40cc-b487-2ef219a5fd0c", "nutritionalInfo": {"allergens": "", "displayString": ""}, "suspendReason": null, "suspendUntil": 0, "classifications": []}, "cd63dd78-eee2-4b88-a0fd-a94f11464205": {"description": "Italian cooked ham, emmenthal cheese, fresh tomato, and rucola salad.", "imageUrl": "", "price": 850, "title": "Genova Panini", "uuid": "cd63dd78-eee2-4b88-a0fd-a94f11464205", "nutritionalInfo": {"allergens": "", "displayString": ""}, "suspendReason": null, "suspendUntil": 0, "classifications": []}, "a0ce592c-bddb-472e-a7f3-d21d2e5a5f11": {"description": " Octopus, fresh tomatoes, rucola salad, and balsamic vinegar.", "imageUrl": "", "price": 1250, "title": "Octopus Salad", "uuid": "a0ce592c-bddb-472e-a7f3-d21d2e5a5f11", "nutritionalInfo": {"allergens": "", "displayString": ""}, "suspendReason": null, "suspendUntil": 0, "classifications": []}, "2999ad0e-3582-4144-8cb4-8eb7770cc36e": {"description": "Salami milano, pecorino cheese, rucola salad, and truffle oil.", "imageUrl": "", "price": 850, "title": "Tartufo Panini", "uuid": "2999ad0e-3582-4144-8cb4-8eb7770cc36e", "nutritionalInfo": {"allergens": "", "displayString": ""}, "suspendReason": null, "suspendUntil": 0, "classifications": []}, "3db2a16a-f98f-4b1a-aaa6-94e8f42494da": {"description": "Topped with shaved parmesan cheese.", "imageUrl": "", "price": 1080, "title": "Hot Spicy 'Nduja' Scrambled Eggs on Toast", "uuid": "3db2a16a-f98f-4b1a-aaa6-94e8f42494da", "nutritionalInfo": {"allergens": "", "displayString": ""}, "suspendReason": null, "suspendUntil": 0, "endorsement": {"text": "Spicy", "iconUrl": "https://uber-test.s3.amazonaws.com/badge_check@3x.png"}, "classifications": []}, "4931fbba-05c1-4ba0-bb9f-70f2507ded28": {"description": "Fresh mozzarella, sun dried tomato, and artichoke.", "imageUrl": "", "price": 850, "title": "Firenze Panini", "uuid": "4931fbba-05c1-4ba0-bb9f-70f2507ded28", "nutritionalInfo": {"allergens": "", "displayString": ""}, "suspendReason": null, "suspendUntil": 0, "endorsement": {"text": "Vegetarian", "iconUrl": "https://uber-test.s3.amazonaws.com/badge_healthy@3x.png"}, "classifications": []}, "5ae47049-6ee0-4f80-849e-b0cec13962f0": {"description": "Goat cheese, sun dried tomato, and pesto sauce.", "imageUrl": "", "price": 850, "title": "Caprino Panini", "uuid": "5ae47049-6ee0-4f80-849e-b0cec13962f0", "nutritionalInfo": {"allergens": "", "displayString": ""}, "suspendReason": null, "suspendUntil": 0, "endorsement": {"text": "Vegetarian", "iconUrl": "https://uber-test.s3.amazonaws.com/badge_healthy@3x.png"}, "classifications": []}, "0fefb1dd-4e3b-4d6e-9218-b18ce3fdd951": {"description": "Italian tuna, fresh tomato, artichoke, and rucola salad.", "imageUrl": "", "price": 850, "title": "Palermo Panini", "uuid": "0fefb1dd-4e3b-4d6e-9218-b18ce3fdd951", "nutritionalInfo": {"allergens": "", "displayString": ""}, "suspendReason": null, "suspendUntil": 0, "classifications": []}, "7dcdee97-d6cd-4512-b9ba-89c687cbb56b": {"description": "Roasted turkey, pesto sauce, sun dried tomato, and rucola salad.", "imageUrl": "", "price": 850, "title": "Modena Panini", "uuid": "7dcdee97-d6cd-4512-b9ba-89c687cbb56b", "nutritionalInfo": {"allergens": "", "displayString": ""}, "suspendReason": null, "suspendUntil": 0, "classifications": []}, "78c1e390-609d-421f-9cd8-1cfa5d7576d9": {"description": "Italian cooked ham and aubergine parmigiana.", "imageUrl": "", "price": 850, "title": "Capitano Panini", "uuid": "78c1e390-609d-421f-9cd8-1cfa5d7576d9", "nutritionalInfo": {"allergens": "", "displayString": ""}, "suspendReason": null, "suspendUntil": 0, "classifications": []}, "61368dba-f538-45fa-8cb9-5058b3082211": {"description": "Grilled artichoke, rucola salad, fresh tomatoes, olives, and shaved  parmesan cheese.", "imageUrl": "", "price": 1150, "title": "Artichoke Salad", "uuid": "61368dba-f538-45fa-8cb9-5058b3082211", "nutritionalInfo": {"allergens": "", "displayString": ""}, "suspendReason": null, "suspendUntil": 0, "classifications": []}, "f1519205-d49c-41c7-9b77-c456df86ac3a": {"description": "breaded Chicken escalope , fresh tomatoes, grilled peppers, aubergine, rucola salad, balsamic, and e.v.o oil.", "imageUrl": "", "price": 1150, "title": "Chicken Salad", "uuid": "f1519205-d49c-41c7-9b77-c456df86ac3a", "nutritionalInfo": {"allergens": "", "displayString": ""}, "suspendReason": null, "suspendUntil": 0, "classifications": []}, "21931c5f-8d23-4e75-8262-49e0647565cf": {"description": "", "imageUrl": "", "price": 180, "title": "Granola", "uuid": "21931c5f-8d23-4e75-8262-49e0647565cf", "nutritionalInfo": {"allergens": "", "displayString": ""}, "suspendReason": null, "suspendUntil": 0, "classifications": []}, "3d22d08a-e4a3-4eb5-9ea3-2856053424a9": {"description": "Buffalo mozzarella, parma ham, rucola salad, sun dried tomato, and pane carasau (flat crispy bread).", "imageUrl": "", "price": 1150, "title": "Buffalo Salad", "uuid": "3d22d08a-e4a3-4eb5-9ea3-2856053424a9", "nutritionalInfo": {"allergens": "", "displayString": ""}, "suspendReason": null, "suspendUntil": 0, "classifications": []}, "d53c4dda-15f3-4e83-a1f0-b0675fbb9acc": {"description": "Topped with banana, honey, and pistachios nuts. Topped with pistachio nuts.", "imageUrl": "", "price": 480, "title": "Porridge\u00a0", "uuid": "d53c4dda-15f3-4e83-a1f0-b0675fbb9acc", "nutritionalInfo": {"allergens": "", "displayString": ""}, "suspendReason": null, "suspendUntil": 0, "classifications": []}, "d356cdfd-28e0-4253-8062-7bb200137e9f": {"description": "", "imageUrl": "", "price": 180, "title": "Sanpellegrino", "uuid": "d356cdfd-28e0-4253-8062-7bb200137e9f", "nutritionalInfo": {"allergens": "", "displayString": ""}, "suspendReason": null, "suspendUntil": 0, "classifications": []}, "ce4c9fee-1709-42a5-88f1-d18ac56025af": {"description": "Roast beef, tomato, rucola salad, olive oil, and balsamic.", "imageUrl": "", "price": 850, "title": "Como Panini", "uuid": "ce4c9fee-1709-42a5-88f1-d18ac56025af", "nutritionalInfo": {"allergens": "", "displayString": ""}, "suspendReason": null, "suspendUntil": 0, "classifications": []}, "fafc6eb3-1715-4d24-8d60-9f3bfbe29031": {"description": "Italian salami, gorgonzola cheese, sun dried tomato, and rucola salad.", "imageUrl": "", "price": 850, "title": "Gorgonzola Panini", "uuid": "fafc6eb3-1715-4d24-8d60-9f3bfbe29031", "nutritionalInfo": {"allergens": "", "displayString": ""}, "suspendReason": null, "suspendUntil": 0, "classifications": []}, "fdc394c0-d62b-4059-8f82-14e22c478b58": {"description": "Smoked salmon, creamy cheese, and rucola salad.", "imageUrl": "", "price": 850, "title": "Delizia Panini", "uuid": "fdc394c0-d62b-4059-8f82-14e22c478b58", "nutritionalInfo": {"allergens": "", "displayString": ""}, "suspendReason": null, "suspendUntil": 0, "classifications": []}, "99efc707-3326-43db-97c5-234987dadd8f": {"description": "With fresh pesto, fresh tomato, rucola leaf and 2 eggs sunny side up.", "imageUrl": "", "price": 1150, "title": "Avocado on Toast\u00a0", "uuid": "99efc707-3326-43db-97c5-234987dadd8f", "nutritionalInfo": {"allergens": "", "displayString": ""}, "suspendReason": null, "suspendUntil": 0, "classifications": []}, "d04800cc-7783-4abe-9c9d-d6ff4d41daba": {"description": "Italian parma ham, fresh mozzarella, and rucola salad.", "imageUrl": "", "price": 850, "title": "Venezia Panini", "uuid": "d04800cc-7783-4abe-9c9d-d6ff4d41daba", "nutritionalInfo": {"allergens": "", "displayString": ""}, "suspendReason": null, "suspendUntil": 0, "classifications": []}, "e1c42404-5107-40d1-8495-0040cc0291ea": {"description": "Speck (smoked parma ham) taleggio cheese, sun-dried tomato, and rucola salad.", "imageUrl": "", "price": 850, "title": "Siena Panini", "uuid": "e1c42404-5107-40d1-8495-0040cc0291ea", "nutritionalInfo": {"allergens": "", "displayString": ""}, "suspendReason": null, "suspendUntil": 0, "classifications": []}, "11a3adcb-a423-4056-8a41-9f24b5d6128d": {"description": "", "imageUrl": "", "price": 1140, "title": "Oven Baked Sea Bass and Side", "uuid": "11a3adcb-a423-4056-8a41-9f24b5d6128d", "nutritionalInfo": {"allergens": "", "displayString": ""}, "suspendReason": null, "suspendUntil": 0, "classifications": []}, "a5dc0c6c-a0f2-4e70-a970-134bde5b4a94": {"description": "Custard and pinenuts.", "imageUrl": "", "price": 350, "title": "Torta della Nonna", "uuid": "a5dc0c6c-a0f2-4e70-a970-134bde5b4a94", "nutritionalInfo": {"allergens": "", "displayString": ""}, "suspendReason": null, "suspendUntil": 0, "classifications": []}, "16ea92b0-834b-4955-9879-e533c07b47a9": {"description": "", "imageUrl": "", "price": 120, "title": "S. Benedetto Still Water", "uuid": "16ea92b0-834b-4955-9879-e533c07b47a9", "nutritionalInfo": {"allergens": "", "displayString": ""}, "suspendReason": null, "suspendUntil": 0, "classifications": []}, "feb181c3-617e-4e7c-8bbf-f54ae8ff08ff": {"description": "Iced tea.", "imageUrl": "", "price": 120, "title": "Estathe", "uuid": "feb181c3-617e-4e7c-8bbf-f54ae8ff08ff", "nutritionalInfo": {"allergens": "", "displayString": ""}, "suspendReason": null, "suspendUntil": 0, "classifications": []}, "ce372108-27bb-46ec-855e-10e849b4f7e5": {"description": "Spicy salami, emmenthal cheese, sun dried tomato, and rucola salad.", "imageUrl": "", "price": 850, "title": "Calabria Panini", "uuid": "ce372108-27bb-46ec-855e-10e849b4f7e5", "nutritionalInfo": {"allergens": "", "displayString": ""}, "suspendReason": null, "suspendUntil": 0, "classifications": []}, "2994077a-1260-4f6f-975f-e3d28c00ba6e": {"description": "Buffalo mozzarella, fresh beef  tomatoes, rucola salad, fresh basil pesto sauce , balsamic and olive oil.", "imageUrl": "", "price": 1150, "title": "Caprese Salad", "uuid": "2994077a-1260-4f6f-975f-e3d28c00ba6e", "nutritionalInfo": {"allergens": "", "displayString": ""}, "suspendReason": null, "suspendUntil": 0, "classifications": []}, "1fd647d5-9f1e-4b7f-8ff7-5b8c9193f6e3": {"description": "Chorizo salami, emmenthal cheese, roasted peppers, and rucola salad.", "imageUrl": "", "price": 850, "title": "Pimlico Panini", "uuid": "1fd647d5-9f1e-4b7f-8ff7-5b8c9193f6e3", "nutritionalInfo": {"allergens": "", "displayString": ""}, "suspendReason": null, "suspendUntil": 0, "classifications": []}, "339bd73a-2de1-438d-89f0-bf7578315a75": {"description": "Italian roasted ham, fresh mozzarella, and fresh tomato.", "imageUrl": "", "price": 850, "title": "Pisa Panini", "uuid": "339bd73a-2de1-438d-89f0-bf7578315a75", "nutritionalInfo": {"allergens": "", "displayString": ""}, "suspendReason": null, "suspendUntil": 0, "classifications": []}, "85ceb05d-7cbb-4e0d-b102-2f985fc4e7f7": {"description": "\"Coca-Cola Classic is the world's favourite soft drink and has been enjoyed since 1886.\n \n Great Coke taste\n Only natural flavours\n No added preservatives\n Gluten-free, dairy-free and nut-free\n \n Serve ice cold for maximum refreshment.\"", "imageUrl": "https://d1ralsognjng37.cloudfront.net/50b7bfb7-2d2b-4793-a7e3-8d89675b6c2d.png", "price": 180, "title": "Coca-Cola Original Taste ", "uuid": "85ceb05d-7cbb-4e0d-b102-2f985fc4e7f7", "nutritionalInfo": {"allergens": "", "displayString": ""}, "suspendReason": null, "suspendUntil": 0, "classifications": []}, "64053ab4-8d7e-4e58-8ed2-18c0f587a0e5": {"description": "", "imageUrl": "", "price": 1140, "title": "Garlic and Honey Salmon and  Side", "uuid": "64053ab4-8d7e-4e58-8ed2-18c0f587a0e5", "nutritionalInfo": {"allergens": "", "displayString": ""}, "suspendReason": null, "suspendUntil": 0, "classifications": []}, "8c08477d-608e-426b-ac3b-2620b415b2e7": {"description": "Chicken escalope, fresh tomato, and rucola salad.", "imageUrl": "", "price": 850, "title": "Torino Panini", "uuid": "8c08477d-608e-426b-ac3b-2620b415b2e7", "nutritionalInfo": {"allergens": "", "displayString": ""}, "suspendReason": null, "suspendUntil": 0, "classifications": []}, "727b2365-4fac-4144-a1fe-0916b3f70213": {"description": "", "imageUrl": "", "price": 120, "title": "Cannolini", "uuid": "727b2365-4fac-4144-a1fe-0916b3f70213", "nutritionalInfo": {"allergens": "", "displayString": ""}, "suspendReason": null, "suspendUntil": 0, "classifications": []}, "e1c8cc75-0494-4b0c-bd46-ac12431a7259": {"description": "", "imageUrl": "", "price": 180, "title": "Chocolate Caramel", "uuid": "e1c8cc75-0494-4b0c-bd46-ac12431a7259", "nutritionalInfo": {"allergens": "", "displayString": ""}, "suspendReason": null, "suspendUntil": 0, "classifications": []}, "e9dca012-19c1-430a-85f3-f7a6656cd9de": {"description": "Meatballs and provolone cheese.", "imageUrl": "", "price": 850, "title": "Nonna Panini", "uuid": "e9dca012-19c1-430a-85f3-f7a6656cd9de", "nutritionalInfo": {"allergens": "", "displayString": ""}, "suspendReason": null, "suspendUntil": 0, "classifications": []}}, "30117e64-faac-4612-b461-9f43b379c425": {"8a3bf40b-d842-4fc4-8dd2-3ab1f1e41075": {"description": "100 grams.", "imageUrl": "", "price": 288, "title": "Roasted Peppers", "uuid": "8a3bf40b-d842-4fc4-8dd2-3ab1f1e41075", "nutritionalInfo": {"allergens": "", "displayString": ""}, "suspendReason": null, "suspendUntil": 0, "classifications": []}, "1a1d3a22-03a4-455d-a6b8-5316cd6d5fa2": {"description": "A selection of vegetarian or meat baby burschetta.", "imageUrl": "", "price": 3600, "title": "Crostini", "uuid": "1a1d3a22-03a4-455d-a6b8-5316cd6d5fa2", "nutritionalInfo": {"allergens": "", "displayString": ""}, "suspendReason": null, "suspendUntil": 0, "classifications": []}, "ea4c1b7d-0681-48bc-bd04-2529e22580dd": {"description": "Slow cook in a rich sauce with mix herbs, served with rice .", "imageUrl": "", "price": 1050, "title": "Beef Stew", "uuid": "ea4c1b7d-0681-48bc-bd04-2529e22580dd", "nutritionalInfo": {"allergens": "", "displayString": ""}, "suspendReason": null, "suspendUntil": 0, "classifications": []}, "bebef6ae-0daa-45ac-ae4c-a9d3188f2ada": {"description": "", "imageUrl": "", "price": 2400, "title": "Pasta Salad", "uuid": "bebef6ae-0daa-45ac-ae4c-a9d3188f2ada", "nutritionalInfo": {"allergens": "", "displayString": ""}, "suspendReason": null, "suspendUntil": 0, "classifications": []}, "4c085deb-e81b-4b2e-8d5b-eab1542c5b24": {"description": "100 grams.", "imageUrl": "", "price": 324, "title": "Home Made Pesto Sauce", "uuid": "4c085deb-e81b-4b2e-8d5b-eab1542c5b24", "nutritionalInfo": {"allergens": "", "displayString": ""}, "suspendReason": null, "suspendUntil": 0, "classifications": []}, "ef4daa76-69ad-489e-a37b-ba6477718a67": {"description": "Each.", "imageUrl": "", "price": 120, "title": "Cannolini", "uuid": "ef4daa76-69ad-489e-a37b-ba6477718a67", "nutritionalInfo": {"allergens": "", "displayString": ""}, "suspendReason": null, "suspendUntil": 0, "classifications": []}, "8e3b4ae6-f857-4a06-abe7-d38a89a9eb23": {"description": "Each.", "imageUrl": "", "price": 120, "title": "Sfogliatelle", "uuid": "8e3b4ae6-f857-4a06-abe7-d38a89a9eb23", "nutritionalInfo": {"allergens": "", "displayString": ""}, "suspendReason": null, "suspendUntil": 0, "classifications": []}, "038063b7-0665-433c-9002-b47165bdc90d": {"description": "", "imageUrl": "", "price": 300, "title": "San Pellegrino", "uuid": "038063b7-0665-433c-9002-b47165bdc90d", "nutritionalInfo": {"allergens": "", "displayString": ""}, "suspendReason": null, "suspendUntil": 0, "classifications": []}, "be45b054-d5ec-484c-bf68-5e6c2f20c990": {"description": "", "imageUrl": "", "price": 3000, "title": "Caprese Salad", "uuid": "be45b054-d5ec-484c-bf68-5e6c2f20c990", "nutritionalInfo": {"allergens": "", "displayString": ""}, "suspendReason": null, "suspendUntil": 0, "classifications": []}, "9c3a21f7-e6f0-4eeb-9892-80346a121e29": {"description": "Prepared freshly using Italian ciabatta or focaccia bread.", "imageUrl": "", "price": 850, "title": "Panini", "uuid": "9c3a21f7-e6f0-4eeb-9892-80346a121e29", "nutritionalInfo": {"allergens": "", "displayString": ""}, "suspendReason": null, "suspendUntil": 0, "classifications": []}, "53c7a131-65a8-4a1d-84f4-39de49128e07": {"description": "100 grams.", "imageUrl": "", "price": 288, "title": "Sun Dried Tomateos", "uuid": "53c7a131-65a8-4a1d-84f4-39de49128e07", "nutritionalInfo": {"allergens": "", "displayString": ""}, "suspendReason": null, "suspendUntil": 0, "classifications": []}, "1d69658e-4061-4c13-9878-ae4486f29d11": {"description": "100 grams.", "imageUrl": "", "price": 250, "title": "Selection of Olives", "uuid": "1d69658e-4061-4c13-9878-ae4486f29d11", "nutritionalInfo": {"allergens": "", "displayString": ""}, "suspendReason": null, "suspendUntil": 0, "classifications": []}, "bc2f02fd-aae0-4acb-9c19-350f4da1c68c": {"description": "Fresh fruit platter.", "imageUrl": "", "price": 2400, "title": "Fresh Fruit Platter", "uuid": "bc2f02fd-aae0-4acb-9c19-350f4da1c68c", "nutritionalInfo": {"allergens": "", "displayString": ""}, "suspendReason": null, "suspendUntil": 0, "classifications": []}, "f9b0a9e7-a28e-45b7-9433-cead441a4898": {"description": "Chicken brest,coated with egg, flour and breadcrumb served with side.", "imageUrl": "", "price": 900, "title": "Chicken Milanese", "uuid": "f9b0a9e7-a28e-45b7-9433-cead441a4898", "nutritionalInfo": {"allergens": "", "displayString": ""}, "suspendReason": null, "suspendUntil": 0, "classifications": []}, "f2cf709c-369f-434f-80d3-6094eaca7641": {"description": "", "imageUrl": "", "price": 4200, "title": "Octopus Salad", "uuid": "f2cf709c-369f-434f-80d3-6094eaca7641", "nutritionalInfo": {"allergens": "", "displayString": ""}, "suspendReason": null, "suspendUntil": 0, "classifications": []}, "ff1f572b-05ea-42c0-adac-dd8b7e3163d7": {"description": "", "imageUrl": "", "price": 180, "title": "Santal Juices", "uuid": "ff1f572b-05ea-42c0-adac-dd8b7e3163d7", "nutritionalInfo": {"allergens": "", "displayString": ""}, "suspendReason": null, "suspendUntil": 0, "classifications": []}, "c7b3cf77-8a7e-4c3c-ac73-eb5a8e09688c": {"description": "A selection of freshly cutted cold meat.", "imageUrl": "", "price": 4500, "title": "Charcuteries", "uuid": "c7b3cf77-8a7e-4c3c-ac73-eb5a8e09688c", "nutritionalInfo": {"allergens": "", "displayString": ""}, "suspendReason": null, "suspendUntil": 0, "classifications": []}, "bc81517f-2e38-414f-89e0-8fbc45e7547f": {"description": "Cooked with garlic roasted tomatoe. Served with rice or spaghetti.", "imageUrl": "", "price": 1150, "title": "Spicy Prawns", "uuid": "bc81517f-2e38-414f-89e0-8fbc45e7547f", "nutritionalInfo": {"allergens": "", "displayString": ""}, "suspendReason": null, "suspendUntil": 0, "endorsement": {"text": "Spicy", "iconUrl": "https://uber-test.s3.amazonaws.com/badge_check@3x.png"}, "classifications": []}, "81129aa2-592f-447a-930f-639006b086fe": {"description": "Beef mincemeat mixed with breadcrumbs, eggs, parmesan, fresh herbs, garlic, and cooked in a tomato sauce.", "imageUrl": "", "price": 660, "title": "Meat Ball", "uuid": "81129aa2-592f-447a-930f-639006b086fe", "nutritionalInfo": {"allergens": "", "displayString": ""}, "suspendReason": null, "suspendUntil": 0, "classifications": []}, "242ada1a-bf9f-4c2c-89b2-1362cf355c22": {"description": "", "imageUrl": "", "price": 120, "title": "San Benedetto Still Water", "uuid": "242ada1a-bf9f-4c2c-89b2-1362cf355c22", "nutritionalInfo": {"allergens": "", "displayString": ""}, "suspendReason": null, "suspendUntil": 0, "classifications": []}, "fcedb9b8-76d3-4bbc-b1ab-81c3a643bbbc": {"description": "Each.", "imageUrl": "", "price": 180, "title": "Mozzarella, Tomatoes, and Olive", "uuid": "fcedb9b8-76d3-4bbc-b1ab-81c3a643bbbc", "nutritionalInfo": {"allergens": "", "displayString": ""}, "suspendReason": null, "suspendUntil": 0, "classifications": []}, "c3ea6c65-b7ea-4342-afd6-b1ff50c36e17": {"description": "Per slice.", "imageUrl": "", "price": 180, "title": "Lemon and Polenta", "uuid": "c3ea6c65-b7ea-4342-afd6-b1ff50c36e17", "nutritionalInfo": {"allergens": "", "displayString": ""}, "suspendReason": null, "suspendUntil": 0, "endorsement": {"text": "Gluten Free", "iconUrl": "https://uber-test.s3.amazonaws.com/badge_check@3x.png"}, "classifications": []}, "591cf8ba-b927-462b-b606-4997594c84ab": {"description": "", "imageUrl": "", "price": 180, "title": "Homemade Meatballs", "uuid": "591cf8ba-b927-462b-b606-4997594c84ab", "nutritionalInfo": {"allergens": "", "displayString": ""}, "suspendReason": null, "suspendUntil": 0, "classifications": []}, "dfedf431-23b5-4af5-bf28-ededcd359e73": {"description": "", "imageUrl": "", "price": 2400, "title": "Tricolore Salad", "uuid": "dfedf431-23b5-4af5-bf28-ededcd359e73", "nutritionalInfo": {"allergens": "", "displayString": ""}, "suspendReason": null, "suspendUntil": 0, "classifications": []}, "1ecb769f-0852-468d-80f1-36392b3d9547": {"description": "Mix leaf.", "imageUrl": "", "price": 1800, "title": "Greek Salad", "uuid": "1ecb769f-0852-468d-80f1-36392b3d9547", "nutritionalInfo": {"allergens": "", "displayString": ""}, "suspendReason": null, "suspendUntil": 0, "classifications": []}, "97c9bfe4-025e-4c44-a0c8-b51d86a63851": {"description": "Serves 10 to 15 people.", "imageUrl": "", "price": 4800, "title": "Rustic Tarts", "uuid": "97c9bfe4-025e-4c44-a0c8-b51d86a63851", "nutritionalInfo": {"allergens": "", "displayString": ""}, "suspendReason": null, "suspendUntil": 0, "classifications": []}, "75ecf743-e1d3-42fa-99a2-401174878986": {"description": "A southern Italian dish made with aubergine slices layered with cheese and tomato sauce, topped with grated parmesan then baked.", "imageUrl": "", "price": 660, "title": "Parmigiana", "uuid": "75ecf743-e1d3-42fa-99a2-401174878986", "nutritionalInfo": {"allergens": "", "displayString": ""}, "suspendReason": null, "suspendUntil": 0, "classifications": []}, "f300717a-6f78-4709-97c6-dada407c3deb": {"description": "Per slice.", "imageUrl": "", "price": 300, "title": "Selection of Home Made Cake", "uuid": "f300717a-6f78-4709-97c6-dada407c3deb", "nutritionalInfo": {"allergens": "", "displayString": ""}, "suspendReason": null, "suspendUntil": 0, "classifications": []}, "f90e8765-5ce7-4d08-b0ea-6eacf6456e09": {"description": "English beef and pork meat cooked in a rich bolognese sauce layered with pasta topped with bechamel sauce and grated parmesan cheese.", "imageUrl": "", "price": 660, "title": "Lasagna", "uuid": "f90e8765-5ce7-4d08-b0ea-6eacf6456e09", "nutritionalInfo": {"allergens": "", "displayString": ""}, "suspendReason": null, "suspendUntil": 0, "classifications": []}, "2840c343-2513-4ee7-a093-ae87e71a2401": {"description": "Per slice.", "imageUrl": "", "price": 300, "title": "Lemon Cake and Biscuits", "uuid": "2840c343-2513-4ee7-a093-ae87e71a2401", "nutritionalInfo": {"allergens": "", "displayString": ""}, "suspendReason": null, "suspendUntil": 0, "classifications": []}, "312a24cb-8d02-42ea-8ec5-c0bac0dd49ec": {"description": "", "imageUrl": "", "price": 120, "title": "San Benedetto Sparkling Water", "uuid": "312a24cb-8d02-42ea-8ec5-c0bac0dd49ec", "nutritionalInfo": {"allergens": "", "displayString": ""}, "suspendReason": null, "suspendUntil": 0, "classifications": []}, "11712bda-70d1-4004-b3c5-ee0c8d37af9f": {"description": "yogurt , granola, banana, honey, pistachio nuts", "imageUrl": "", "price": 495, "title": "Yogurt and Granola Pot", "uuid": "11712bda-70d1-4004-b3c5-ee0c8d37af9f", "nutritionalInfo": {"allergens": "", "displayString": ""}, "suspendReason": null, "suspendUntil": 0, "classifications": []}, "812643f0-f4db-4aba-8d66-d92718b69b68": {"description": "Each.", "imageUrl": "", "price": 240, "title": "King Prawns", "uuid": "812643f0-f4db-4aba-8d66-d92718b69b68", "nutritionalInfo": {"allergens": "", "displayString": ""}, "suspendReason": null, "suspendUntil": 0, "classifications": []}, "a422c401-7192-4b06-aba8-af1936438a2a": {"description": "Selection of freshly cut cheese. Served with biscuits and fruit.", "imageUrl": "", "price": 4500, "title": "Cheese Board", "uuid": "a422c401-7192-4b06-aba8-af1936438a2a", "nutritionalInfo": {"allergens": "", "displayString": ""}, "suspendReason": null, "suspendUntil": 0, "classifications": []}, "b7cbf866-9d8b-45fd-b21b-40ab847b9bf6": {"description": "Fresh egg pasta filled with spinach and ricotta on a tomato and basil sauce baked with bechamel and grated parmesan.", "imageUrl": "", "price": 800, "title": "Cannelloni", "uuid": "b7cbf866-9d8b-45fd-b21b-40ab847b9bf6", "nutritionalInfo": {"allergens": "", "displayString": ""}, "suspendReason": null, "suspendUntil": 0, "classifications": []}}}, "sections": [{"subsectionUuids": ["6466b860-505d-413a-8f55-ad6d2de3a435", "a6f81364-8679-403d-a51a-204371dd1584", "8b28480c-07a6-4b85-9c38-4ee4e8ae7896", "47c51955-81c8-48df-b9af-35615f6b2a79", "9b3e5356-a5e0-405a-bfa1-2398cf89f730", "48271973-befe-497a-aa53-d4818361a242", "e0fefd15-e0ef-49b4-a244-a9759243c8ef"], "title": "Menu", "subtitle": "10:00 AM \u2013 6:00 PM", "uuid": "44900d29-2bfc-4ece-962c-cd1a7f3f9b4e", "isTop": true, "isOnSale": true}, {"subsectionUuids": ["f4097623-0377-44e8-9c21-3619e204ad6d", "95d775c3-e1b4-4b56-b803-fe82e79a61bc", "13298f76-5bd3-438e-883c-042468ce5338", "d2805fef-5b57-466f-9a5c-8ad8b9a08873", "52e14c28-3e82-40ab-84f3-3105062efb0f", "b116fe2f-f90d-4fc5-9322-7e86ee54fbea", "16ecc61e-f61c-4d06-87e0-eef6843715ca", "da2539d5-c1b7-4a0d-ac0d-1149ff4f5a20"], "title": "Catering", "subtitle": "Closed", "uuid": "30117e64-faac-4612-b461-9f43b379c425", "isTop": false, "isOnSale": false}], "subsectionsMap": {"9b3e5356-a5e0-405a-bfa1-2398cf89f730": {"itemUuids": ["6d6da4b8-392e-40c0-aa90-ba1a4d402836", "5ce22712-de1d-4a7d-ab71-b076d33e2414", "ced64950-deda-4996-8193-96e622b94a9f", "eba39688-a77a-4f6a-ba35-f35f9874d077", "64053ab4-8d7e-4e58-8ed2-18c0f587a0e5", "11a3adcb-a423-4056-8a41-9f24b5d6128d", "132e5c00-8a07-449e-9293-7391d39ed789"], "subtitle": null, "title": "Mains Primi", "uuid": "9b3e5356-a5e0-405a-bfa1-2398cf89f730", "displayType": null}, "8b28480c-07a6-4b85-9c38-4ee4e8ae7896": {"itemUuids": ["0fefb1dd-4e3b-4d6e-9218-b18ce3fdd951", "4ef885f7-eedf-4464-a98b-a05f0896e812", "7dcdee97-d6cd-4512-b9ba-89c687cbb56b", "ce4c9fee-1709-42a5-88f1-d18ac56025af", "2999ad0e-3582-4144-8cb4-8eb7770cc36e", "cd63dd78-eee2-4b88-a0fd-a94f11464205", "fafc6eb3-1715-4d24-8d60-9f3bfbe29031", "fdc394c0-d62b-4059-8f82-14e22c478b58", "ce372108-27bb-46ec-855e-10e849b4f7e5", "339bd73a-2de1-438d-89f0-bf7578315a75", "24320977-a738-4492-920f-257200b527f5", "8c08477d-608e-426b-ac3b-2620b415b2e7", "8392f684-396f-4afb-bc55-81cc35df1f33", "d04800cc-7783-4abe-9c9d-d6ff4d41daba", "e9dca012-19c1-430a-85f3-f7a6656cd9de", "e1c42404-5107-40d1-8495-0040cc0291ea", "78c1e390-609d-421f-9cd8-1cfa5d7576d9", "1fd647d5-9f1e-4b7f-8ff7-5b8c9193f6e3"], "subtitle": null, "title": "Freshly Made Panini", "uuid": "8b28480c-07a6-4b85-9c38-4ee4e8ae7896", "displayType": null}, "47c51955-81c8-48df-b9af-35615f6b2a79": {"itemUuids": ["ce5348f3-47ff-47e7-997f-a382c5440d20", "4931fbba-05c1-4ba0-bb9f-70f2507ded28", "18f91770-4f91-449a-9448-a00e63b02ff2", "19d87344-b6fa-4f0f-a30e-524f4e21862e", "5ae47049-6ee0-4f80-849e-b0cec13962f0"], "subtitle": null, "title": "Vegetarian Panini", "uuid": "47c51955-81c8-48df-b9af-35615f6b2a79", "displayType": null}, "95d775c3-e1b4-4b56-b803-fe82e79a61bc": {"itemUuids": ["1a1d3a22-03a4-455d-a6b8-5316cd6d5fa2", "97c9bfe4-025e-4c44-a0c8-b51d86a63851", "f2cf709c-369f-434f-80d3-6094eaca7641", "bc2f02fd-aae0-4acb-9c19-350f4da1c68c", "c7b3cf77-8a7e-4c3c-ac73-eb5a8e09688c", "a422c401-7192-4b06-aba8-af1936438a2a", "9c3a21f7-e6f0-4eeb-9892-80346a121e29"], "subtitle": null, "title": "Mains", "uuid": "95d775c3-e1b4-4b56-b803-fe82e79a61bc", "displayType": null}, "da2539d5-c1b7-4a0d-ac0d-1149ff4f5a20": {"itemUuids": ["8e3b4ae6-f857-4a06-abe7-d38a89a9eb23", "2840c343-2513-4ee7-a093-ae87e71a2401", "c3ea6c65-b7ea-4342-afd6-b1ff50c36e17"], "subtitle": null, "title": "Cake and Biscuits", "uuid": "da2539d5-c1b7-4a0d-ac0d-1149ff4f5a20", "displayType": null}, "e0fefd15-e0ef-49b4-a244-a9759243c8ef": {"itemUuids": ["5bbff582-1c0b-4fa8-8898-05db44ab7e14", "727b2365-4fac-4144-a1fe-0916b3f70213", "21931c5f-8d23-4e75-8262-49e0647565cf", "840f2a99-4eef-41e7-b57b-b11c9d889595", "e1c8cc75-0494-4b0c-bd46-ac12431a7259", "a5dc0c6c-a0f2-4e70-a970-134bde5b4a94", "f5b22713-fac9-4d23-80e8-af77aef0f1b0", "eff3c868-5bf3-40b0-9012-f17b91384e47"], "subtitle": null, "title": "Sweet Bites", "uuid": "e0fefd15-e0ef-49b4-a244-a9759243c8ef", "displayType": null}, "13298f76-5bd3-438e-883c-042468ce5338": {"itemUuids": ["11712bda-70d1-4004-b3c5-ee0c8d37af9f", "f300717a-6f78-4709-97c6-dada407c3deb", "8e3b4ae6-f857-4a06-abe7-d38a89a9eb23", "ef4daa76-69ad-489e-a37b-ba6477718a67"], "subtitle": null, "title": "Breakfast Mains", "uuid": "13298f76-5bd3-438e-883c-042468ce5338", "displayType": null}, "16ecc61e-f61c-4d06-87e0-eef6843715ca": {"itemUuids": ["038063b7-0665-433c-9002-b47165bdc90d", "242ada1a-bf9f-4c2c-89b2-1362cf355c22", "312a24cb-8d02-42ea-8ec5-c0bac0dd49ec", "ff1f572b-05ea-42c0-adac-dd8b7e3163d7"], "subtitle": null, "title": "Beverages", "uuid": "16ecc61e-f61c-4d06-87e0-eef6843715ca", "displayType": null}, "a6f81364-8679-403d-a51a-204371dd1584": {"itemUuids": ["b7076d8f-2fdb-4ae3-b6a8-5816cac85a06", "d53c4dda-15f3-4e83-a1f0-b0675fbb9acc", "408a244e-30f4-4525-aef1-776e990f455a", "bc626897-39ac-40cc-b487-2ef219a5fd0c", "99efc707-3326-43db-97c5-234987dadd8f", "3db2a16a-f98f-4b1a-aaa6-94e8f42494da"], "subtitle": null, "title": "Breakfast Mains", "uuid": "a6f81364-8679-403d-a51a-204371dd1584", "displayType": null}, "d2805fef-5b57-466f-9a5c-8ad8b9a08873": {"itemUuids": ["fcedb9b8-76d3-4bbc-b1ab-81c3a643bbbc", "812643f0-f4db-4aba-8d66-d92718b69b68", "591cf8ba-b927-462b-b606-4997594c84ab"], "subtitle": null, "title": "Skewers/Spiedini", "uuid": "d2805fef-5b57-466f-9a5c-8ad8b9a08873", "displayType": null}, "f4097623-0377-44e8-9c21-3619e204ad6d": {"itemUuids": ["1ecb769f-0852-468d-80f1-36392b3d9547", "dfedf431-23b5-4af5-bf28-ededcd359e73", "bebef6ae-0daa-45ac-ae4c-a9d3188f2ada", "be45b054-d5ec-484c-bf68-5e6c2f20c990"], "subtitle": null, "title": "Salad", "uuid": "f4097623-0377-44e8-9c21-3619e204ad6d", "displayType": null}, "52e14c28-3e82-40ab-84f3-3105062efb0f": {"itemUuids": ["4c085deb-e81b-4b2e-8d5b-eab1542c5b24", "1d69658e-4061-4c13-9878-ae4486f29d11", "53c7a131-65a8-4a1d-84f4-39de49128e07", "8a3bf40b-d842-4fc4-8dd2-3ab1f1e41075"], "subtitle": null, "title": "Extras", "uuid": "52e14c28-3e82-40ab-84f3-3105062efb0f", "displayType": null}, "48271973-befe-497a-aa53-d4818361a242": {"itemUuids": ["d356cdfd-28e0-4253-8062-7bb200137e9f", "85ceb05d-7cbb-4e0d-b102-2f985fc4e7f7", "8abe6aef-3387-4cdb-a92d-d9f82e6cf31b", "feb181c3-617e-4e7c-8bbf-f54ae8ff08ff", "7e4f9038-cd60-4f16-81d7-b1f52170a6b0", "ff1f572b-05ea-42c0-adac-dd8b7e3163d7", "da15367d-0ffc-459e-9b0f-49f8146eea02", "16ea92b0-834b-4955-9879-e533c07b47a9", "91fe261b-05d2-4c09-a2bc-9d4a7c8376ec"], "subtitle": null, "title": "Beverages", "uuid": "48271973-befe-497a-aa53-d4818361a242", "displayType": null}, "b116fe2f-f90d-4fc5-9322-7e86ee54fbea": {"itemUuids": ["f90e8765-5ce7-4d08-b0ea-6eacf6456e09", "75ecf743-e1d3-42fa-99a2-401174878986", "b7cbf866-9d8b-45fd-b21b-40ab847b9bf6", "81129aa2-592f-447a-930f-639006b086fe", "ea4c1b7d-0681-48bc-bd04-2529e22580dd", "bc81517f-2e38-414f-89e0-8fbc45e7547f", "f9b0a9e7-a28e-45b7-9433-cead441a4898"], "subtitle": null, "title": "Mains Primi", "uuid": "b116fe2f-f90d-4fc5-9322-7e86ee54fbea", "displayType": null}, "6466b860-505d-413a-8f55-ad6d2de3a435": {"itemUuids": ["a0ce592c-bddb-472e-a7f3-d21d2e5a5f11", "3d22d08a-e4a3-4eb5-9ea3-2856053424a9", "ce390917-c73a-4295-b843-ac9860d36c3a", "f25cf43a-afc3-473d-9314-3a1a99ffe13b", "f1519205-d49c-41c7-9b77-c456df86ac3a", "6967df7d-c3a9-4727-930d-a4c4c4638a59", "61368dba-f538-45fa-8cb9-5058b3082211", "2994077a-1260-4f6f-975f-e3d28c00ba6e"], "subtitle": null, "title": "Salad", "uuid": "6466b860-505d-413a-8f55-ad6d2de3a435", "displayType": null}}, "title": "Delizie d\u2019italia", "uuid": "30e719a8-9ab4-435b-ba61-7aa5480a00db", "cityId": 18, "categories": ["\u20ac\u20ac", "Fr\u00fchst\u00fcck und Brunch", "Salate", "Sandwiches"], "cuisineList": ["Fr\u00fchst\u00fcck und Brunch", "Salate", "Sandwiches"], "priceBucket": "\u20ac\u20ac", "etaRange": null, "ratingBadge": null, "disclaimerBadge": {"text": "<span>Delizie d&#x2019;italia has a FHRS rating of 3. This information was updated on 06/02/2020. The current rating is on their page on the <a href=\"https://ratings.food.gov.uk/business/en-GB/413407\" style=\"color:#61ad5f;\">FSA Website</a>. Allergies, intolerances and dietary requirements: Before ordering, please contact the restaurant directly and ask to speak to a member of staff who can assist if you require information about ingredients and help cater for your needs.</span>"}, "distanceBadge": null, "fareBadge": null, "fareInfo": {"serviceFeeCents": null}, "promotion": null, "shouldIndex": true, "heroImageUrls": [{"url": "https://d1ralsognjng37.cloudfront.net/f3f369e4-d0ca-4264-9c83-ce0d3eb74c71", "width": 240}, {"url": "https://d1ralsognjng37.cloudfront.net/c90ee29e-571e-4fc1-a039-47b13ef122b5", "width": 550}, {"url": "https://d1ralsognjng37.cloudfront.net/12c37e76-d000-4c12-b4d6-f07d3174bcee", "width": 640}, {"url": "https://d1ralsognjng37.cloudfront.net/1d9c872a-e31f-475c-b9b1-60341c2f86d0", "width": 750}, {"url": "https://d1ralsognjng37.cloudfront.net/850dc512-8902-4b24-a78c-5bef7e648345", "width": 1080}, {"url": "https://d1ralsognjng37.cloudfront.net/b3927c09-0d02-4ca5-a902-4f0edb53177c", "width": 2880}], "isOpen": false, "currencyCode": "GBP", "closedMessage": "Currently unavailable", "location": {"address": "70 Lupus St, England SW1V 3EJ", "streetAddress": "70 Lupus St", "city": "", "country": "GB", "postalCode": "SW1V 3EJ", "region": "England", "latitude": 51.4879741, "longitude": -0.1407063}, "isDeliveryBandwagon": false, "isDeliveryOverTheTop": false, "isDeliveryThirdParty": false, "hours": [{"dayRange": "Sunday", "sectionHours": [{"startTime": 600, "endTime": 1080, "sectionTitle": ""}]}, {"dayRange": "Monday - Friday", "sectionHours": [{"startTime": 540, "endTime": 1140, "sectionTitle": ""}]}, {"dayRange": "Saturday", "sectionHours": [{"startTime": 540, "endTime": 1080, "sectionTitle": ""}]}], "disableOrderInstruction": false, "disableCheckoutInstruction": false, "nuggets": [], "isWithinDeliveryRange": true, "slug": "delizie-ditalia", "citySlug": "london", "phoneNumber": "+442078341471", "metaJson": "{\"@context\":\"http://schema.org\",\"@type\":\"Restaurant\",\"@id\":\"https://www.ubereats.com/en-GB/london/food-delivery/delizie-ditalia/MOcZqJq0Q1u6YXqlSAoA2w\",\"name\":\"Delizie d\u2019italia\",\"servesCuisine\":[\"Fr\u00fchst\u00fcck und Brunch\",\"Salate\",\"Sandwiches\"],\"priceRange\":\"\u20ac\u20ac\",\"image\":[\"https://d1ralsognjng37.cloudfront.net/f3f369e4-d0ca-4264-9c83-ce0d3eb74c71\",\"https://d1ralsognjng37.cloudfront.net/c90ee29e-571e-4fc1-a039-47b13ef122b5\",\"https://d1ralsognjng37.cloudfront.net/12c37e76-d000-4c12-b4d6-f07d3174bcee\",\"https://d1ralsognjng37.cloudfront.net/1d9c872a-e31f-475c-b9b1-60341c2f86d0\",\"https://d1ralsognjng37.cloudfront.net/850dc512-8902-4b24-a78c-5bef7e648345\",\"https://d1ralsognjng37.cloudfront.net/b3927c09-0d02-4ca5-a902-4f0edb53177c\"],\"potentialAction\":{\"@type\":\"OrderAction\",\"target\":{\"@type\":\"EntryPoint\",\"urlTemplate\":\"https://www.ubereats.com/en-GB/london/food-delivery/delizie-ditalia/MOcZqJq0Q1u6YXqlSAoA2w?utm_campaign=order-action&utm_medium=organic\",\"inLanguage\":\"English\",\"actionPlatform\":[\"http://schema.org/DesktopWebPlatform\",\"http://schema.org/MobileWebPlatform\"]},\"deliveryMethod\":[\"http://purl.org/goodrelations/v1#DeliveryModeOwnFleet\"]},\"geo\":{\"@type\":\"GeoCoordinates\",\"latitude\":51.4879741,\"longitude\":-0.1407063},\"telephone\":\"+442078341471\",\"aggregateRating\":{},\"openingHoursSpecification\":[{\"@type\":\"OpeningHoursSpecification\",\"dayOfWeek\":\"Sunday\",\"opens\":\"10:0\",\"closes\":\"18:0\"},{\"@type\":\"OpeningHoursSpecification\",\"dayOfWeek\":[\"Monday\",\"Tuesday\",\"Wednesday\",\"Thursday\",\"Friday\"],\"opens\":\"9:0\",\"closes\":\"19:0\"},{\"@type\":\"OpeningHoursSpecification\",\"dayOfWeek\":\"Saturday\",\"opens\":\"9:0\",\"closes\":\"18:0\"}]}", "promoTrackings": [], "suggestedPromotion": {"text": "", "promotionUuid": ""}, "supportedDiningModes": [{"mode": "DELIVERY", "title": "Delivery", "isSelected": true, "isAvailable": true}], "isPreview": false, "isFavorite": false, "pinnedInfo": null}